[{"name":"Plain","plain":[{"w":"ぐ"}],"formal":[{"w":"ぎます"}]},{"name":"Plain neg.","plain":[{"w":"がない"},{"w":"がず＋に"},{"w":"がぬ","t":[["old","archaic; formal form"]]}],"formal":[{"w":"ぎません"}]},{"name":"Past","plain":[{"w":"いだ"}],"formal":[{"w":"ぎました"}]},{"name":"Past neg.","plain":[{"w":"がなかった"}],"formal":[{"w":"ぎませんでした"}]},{"name":"Provisional","plain":[{"w":"げば"}],"formal":[{"w":"ぎますなら"},{"w":"ぎませば"}]},{"name":"Prov. neg.","plain":[{"w":"がなければ"},{"w":"がなくちゃ","t":[["informal","informal / colloquial / contraction form"]]},{"w":"がなきゃ","t":[["informal","informal / colloquial / contraction form"]]}],"formal":[{"w":"ぎませんなら"}]},{"name":"Conditional","plain":[{"w":"いだら"}],"formal":[{"w":"ぎましたら"}]},{"name":"Cond. neg.","plain":[{"w":"がなかったら"}],"formal":[{"w":"ぎませんでしたら"}]},{"name":"Imperative","plain":[{"w":"げ"}],"formal":[{"w":"ぎなさい"}]},{"name":"Imperative neg.","plain":[{"w":"ぐな"}],"formal":[{"w":"ぎなさるな"}]},{"name":"Volitional","plain":[{"w":"ごう"}],"formal":[{"w":"ぎましょう"}]},{"name":"Volitional neg.","plain":[{"w":"ぐまい","t":[["rare","lit.\tvery rare literary form"]]}],"formal":[{"w":"ぎますまい","t":[["rare","lit.\tvery rare literary form"]]}]},{"name":"Causative","plain":[{"w":"がせる"},{"w":"がす"}],"formal":[{"w":"がせます"},{"w":"がします"}]},{"name":"Causative neg.","plain":[{"w":"がせない"},{"w":"がさない"}],"formal":[{"w":"がせません"},{"w":"がしません"}]},{"name":"Caus. passive","plain":[{"w":"がせられる"},{"w":"がされる"}],"formal":[{"w":"がせられます"},{"w":"がされます"}]},{"name":"Caus. pass. neg.","plain":[{"w":"がせられない"},{"w":"がされない"}],"formal":[{"w":"がせられません"},{"w":"がされません"}]},{"name":"Passive","plain":[{"w":"がれる"}],"formal":[{"w":"がれます"}]},{"name":"Passive neg.","plain":[{"w":"がれない"}],"formal":[{"w":"がれません"}]},{"name":"Potential","plain":[{"w":"げる"}],"formal":[{"w":"げます"}]},{"name":"Potential neg.","plain":[{"w":"げない"}],"formal":[{"w":"げません"}]},{"name":"Conjectural","plain":[{"w":"ぐだろう"}],"formal":[{"w":"ぐでしょう"}]},{"name":"Conjectural neg.","plain":[{"w":"がないだろう"}],"formal":[{"w":"がないでしょう"}]},{"name":"Alternative","plain":[{"w":"いだり"}],"formal":[{"w":"ぎましたり"}]},{"name":"Alternative neg.","plain":[{"w":"がなかったり"}],"formal":[{"w":"ぎませんでしたり"}]},{"name":"-i form","plain":[{"w":"ぎ"}]},{"name":"-te form","plain":[{"w":"いで"}],"formal":[{"w":"ぎまして"}]},{"name":"-te form neg.","plain":[{"w":"がなくて"},{"w":"がないで"}],"formal":[{"w":"ぎませんで"}]},{"name":"-tekudasai","plain":[{"w":"いでください"}],"formal":[{"w":"いでくださいます"}]},{"name":"-teageru","plain":[{"w":"いであげる"}],"formal":[{"w":"いであげます"}]},{"name":"-teiru","plain":[{"w":"いでいる"},{"w":"いでる","t":[["informal","informal / colloquial / contraction form"]]}],"formal":[{"w":"いでいます"}]},{"name":"-teita","plain":[{"w":"いでいた"}],"formal":[{"w":"いでいました"}]},{"name":"-teinai","plain":[{"w":"いでいない"}],"formal":[{"w":"いでいません"}]},{"name":"-tenai","plain":[{"w":"いでない"}],"formal":[{"w":"いでません"}]},{"name":"-teitadaku","plain":[{"w":"いでいただく"}],"formal":[{"w":"いでいただきます"}]},{"name":"-teitadaita","plain":[{"w":"いでいただいた"}],"formal":[{"w":"いでいただきました"}]},{"name":"-temorau","plain":[{"w":"いでもらう"}],"formal":[{"w":"いでもらいます"}]},{"name":"-temoratta","plain":[{"w":"いでもらった"}],"formal":[{"w":"いでもらいました"}]},{"name":"-tekara","plain":[{"w":"いでから"}]},{"name":"-tekureru","plain":[{"w":"いでくれる"}],"formal":[{"w":"いでくれます"}]},{"name":"-tekuru","plain":[{"w":"いでくる"}],"formal":[{"w":"いできます"}]},{"name":"-tekita","plain":[{"w":"いできた"}],"formal":[{"w":"いできました"}]},{"name":"-teiku","plain":[{"w":"いでいく"}],"formal":[{"w":"いでいきます"}]},{"name":"-teitta","plain":[{"w":"いでいった"}],"formal":[{"w":"いでいきました"}]},{"name":"-temiru","plain":[{"w":"いでみる"}],"formal":[{"w":"いでみます"}]},{"name":"-temita","plain":[{"w":"いでみた"}],"formal":[{"w":"いでみました"}]},{"name":"-tegoran","plain":[{"w":"いでごらん"}]},{"name":"-tegorannasai","plain":[{"w":"いでごらんなさい"}]},{"name":"-temoii","plain":[{"w":"いでもいい"}],"formal":[{"w":"いでもよろしい"}]},{"name":"-teoku","plain":[{"w":"いでおく"}],"formal":[{"w":"いでおきます"}]},{"name":"-teshimau","plain":[{"w":"いでしまう"}],"formal":[{"w":"いでしまいます"}]},{"name":"-teshimatta","plain":[{"w":"いでしまった"}],"formal":[{"w":"いでしまいました"}]},{"name":"-tewaikemasen","plain":[{"w":"いではいけません"}],"formal":[{"w":"いではいけません"}]},{"name":"-tenakereba","plain":[{"w":"いでなければ"}]},{"name":"-tenakattara","plain":[{"w":"いでなかったら"}]}]